odoo/addons/hr_employee_firstname/README.rst
odoo/addons/hr_employee_firstname/__init__.py
odoo/addons/hr_employee_firstname/__manifest__.py
odoo/addons/hr_employee_firstname/init_hook.py
odoo/addons/hr_employee_firstname/i18n/ar.po
odoo/addons/hr_employee_firstname/i18n/cs_CZ.po
odoo/addons/hr_employee_firstname/i18n/de.po
odoo/addons/hr_employee_firstname/i18n/es.po
odoo/addons/hr_employee_firstname/i18n/fa.po
odoo/addons/hr_employee_firstname/i18n/fi.po
odoo/addons/hr_employee_firstname/i18n/fr.po
odoo/addons/hr_employee_firstname/i18n/hr.po
odoo/addons/hr_employee_firstname/i18n/hr_HR.po
odoo/addons/hr_employee_firstname/i18n/hr_employee_firstname.pot
odoo/addons/hr_employee_firstname/i18n/it.po
odoo/addons/hr_employee_firstname/i18n/lt.po
odoo/addons/hr_employee_firstname/i18n/nl_NL.po
odoo/addons/hr_employee_firstname/i18n/pt_BR.po
odoo/addons/hr_employee_firstname/i18n/ro.po
odoo/addons/hr_employee_firstname/i18n/sl.po
odoo/addons/hr_employee_firstname/models/__init__.py
odoo/addons/hr_employee_firstname/models/hr_employee.py
odoo/addons/hr_employee_firstname/readme/CONTRIBUTORS.rst
odoo/addons/hr_employee_firstname/readme/DESCRIPTION.rst
odoo/addons/hr_employee_firstname/readme/USAGE.rst
odoo/addons/hr_employee_firstname/static/description/icon.png
odoo/addons/hr_employee_firstname/static/description/index.html
odoo/addons/hr_employee_firstname/tests/__init__.py
odoo/addons/hr_employee_firstname/tests/test_hr_employee_firstname.py
odoo/addons/hr_employee_firstname/views/hr_view.xml
odoo12_addon_hr_employee_firstname-12.0.1.0.1.dist-info/METADATA
odoo12_addon_hr_employee_firstname-12.0.1.0.1.dist-info/WHEEL
odoo12_addon_hr_employee_firstname-12.0.1.0.1.dist-info/top_level.txt
odoo12_addon_hr_employee_firstname-12.0.1.0.1.dist-info/RECORD
