Metadata-Version: 2.1
Name: odoo12-addon-hr-employee-firstname
Version: 12.0.1.0.1
Summary: Adds First Name to Employee
Home-page: https://github.com/OCA/hr/
Author: Savoir-faire Linux, Fekete Mihai (Forest and Biomass Services Romania), Onestein, Odoo Community Association (OCA)
Author-email: support@odoo-community.org
License: AGPL-3
Platform: UNKNOWN
Classifier: Programming Language :: Python
Classifier: Framework :: Odoo
Classifier: License :: OSI Approved :: GNU Affero General Public License v3
Requires-Python: >=3.5
Requires-Dist: odoo12-addon-partner-firstname
Requires-Dist: odoo (<12.1dev,>=12.0a)
